agentql/__init__.py
agentql/_cli/__init__.py
agentql/_cli/_main.py
agentql/_cli/_commands/__init__.py
agentql/_cli/_commands/_utils.py
agentql/_cli/_commands/doctor_command.py
agentql/_cli/_commands/init_command.py
agentql/_cli/_commands/new_script_command.py
agentql/_core/__init__.py
agentql/_core/_api_constants.py
agentql/_core/_config.py
agentql/_core/_errors.py
agentql/_core/_typing.py
agentql/_core/_utils.py
agentql/_core/_js_snippets/__init__.py
agentql/_core/_js_snippets/add_dom_change_listener.js
agentql/_core/_js_snippets/generate_accessibility_tree.js
agentql/_core/_js_snippets/get_last_dom_change.js
agentql/_core/_js_snippets/get_scroll_info.js
agentql/_core/_js_snippets/iframe_contains_doc_or_body.js
agentql/_core/_js_snippets/remove_dom_change_listener.js
agentql/_core/_js_snippets/set_iframe_path.js
agentql/_core/_js_snippets/snippet_loader.py
agentql/_core/_syntax/__init__.py
agentql/_core/_syntax/character_utils.py
agentql/_core/_syntax/lexer.py
agentql/_core/_syntax/node.py
agentql/_core/_syntax/parser.py
agentql/_core/_syntax/source.py
agentql/_core/_syntax/token.py
agentql/_core/_syntax/token_kind.py
agentql/async_api/__init__.py
agentql/async_api/_agentql_service.py
agentql/async_api/_api.py
agentql/ext/__init__.py
agentql/ext/playwright/__init__.py
agentql/ext/playwright/_driver_constants.py
agentql/ext/playwright/_network_monitor.py
agentql/ext/playwright/_response_proxy_base.py
agentql/ext/playwright/_utils.py
agentql/ext/playwright/constants.py
agentql/ext/playwright/async_api/__init__.py
agentql/ext/playwright/async_api/_utils_async.py
agentql/ext/playwright/async_api/playwright_smart_locator.py
agentql/ext/playwright/async_api/response_proxy.py
agentql/ext/playwright/sync_api/__init__.py
agentql/ext/playwright/sync_api/_utils_sync.py
agentql/ext/playwright/sync_api/playwright_smart_locator.py
agentql/ext/playwright/sync_api/response_proxy.py
agentql/ext/playwright/tools/_shared/__init__.py
agentql-1.17.1.dist-info/METADATA
agentql-1.17.1.dist-info/WHEEL
agentql-1.17.1.dist-info/entry_points.txt
agentql-1.17.1.dist-info/licenses/LICENSE
agentql-1.17.1.dist-info/RECORD
